autorunpy/__init__.py
autorunpy/make_venv.py
autorunpy/ret_module_2_run.py
autorunpy/ret_pkg_name.py
autorunpy/rm_venv.py
autorunpy/util.py
autorunpy-8.1.13.dist-info/METADATA
autorunpy-8.1.13.dist-info/WHEEL
autorunpy-8.1.13.dist-info/licenses/LICENSE
autorunpy-8.1.13.dist-info/RECORD
