Metadata-Version: 2.3
Name: autorunpy
Version: 8.1.13
Summary: Tools for auto running python scripts
Author-email: Mahdi Mir <imahdimir@gmail.com>
License: MIT License
License-File: LICENSE
